LICENSE
MANIFEST.in
README.md
setup.py
bin/clairvoyance.py
bin/run_soothsayer.py
soothsayer/__init__.py
soothsayer.egg-info/Icon
soothsayer.egg-info/PKG-INFO
soothsayer.egg-info/SOURCES.txt
soothsayer.egg-info/dependency_links.txt
soothsayer.egg-info/requires.txt
soothsayer.egg-info/top_level.txt
soothsayer/classification/__init__.py
soothsayer/classification/classification.py
soothsayer/core/__init__.py
soothsayer/core/core.py
soothsayer/db/Icon
soothsayer/db/README.md
soothsayer/db/__init__.py
soothsayer/db/db.py
soothsayer/db/kegg-module_ko00002_v2020-11-24.json
soothsayer/db/kegg-module_v2017-06-14.flat
soothsayer/db/kegg-module_v2021-03-22.flat
soothsayer/db/kegg-ortholog_ko00001_v2021-03-21.json
soothsayer/db/pfam.pbz2
soothsayer/db/tigrfam.pbz2
soothsayer/db/Archaea_76/Icon
soothsayer/db/Archaea_76/LICENSE.txt
soothsayer/db/Archaea_76/README.txt
soothsayer/db/Archaea_76/genes.hmm.gz
soothsayer/db/Archaea_76/genes.txt
soothsayer/db/Archaea_76/kind.txt
soothsayer/db/Archaea_76/noise_cutoff_terms.txt
soothsayer/db/Archaea_76/reference.txt
soothsayer/db/Archaea_76/source.txt
soothsayer/db/Archaea_76/target.txt
soothsayer/db/Bacteria_71/Icon
soothsayer/db/Bacteria_71/LICENSE.txt
soothsayer/db/Bacteria_71/README.txt
soothsayer/db/Bacteria_71/genes.hmm.gz
soothsayer/db/Bacteria_71/genes.txt
soothsayer/db/Bacteria_71/kind.txt
soothsayer/db/Bacteria_71/noise_cutoff_terms.txt
soothsayer/db/Bacteria_71/reference.txt
soothsayer/db/Bacteria_71/source.txt
soothsayer/db/Bacteria_71/target.txt
soothsayer/db/Protista_83/Icon
soothsayer/db/Protista_83/LICENSE.txt
soothsayer/db/Protista_83/README.txt
soothsayer/db/Protista_83/genes.hmm.gz
soothsayer/db/Protista_83/genes.txt
soothsayer/db/Protista_83/kind.txt
soothsayer/db/Protista_83/noise_cutoff_terms.txt
soothsayer/db/Protista_83/reference.txt
soothsayer/db/Protista_83/source.txt
soothsayer/db/Protista_83/target.txt
soothsayer/db/Ribosomal_RNAs/Icon
soothsayer/db/Ribosomal_RNAs/LICENSE.txt
soothsayer/db/Ribosomal_RNAs/README.txt
soothsayer/db/Ribosomal_RNAs/genes.hmm.gz
soothsayer/db/Ribosomal_RNAs/genes.txt
soothsayer/db/Ribosomal_RNAs/kind.txt
soothsayer/db/Ribosomal_RNAs/noise_cutoff_terms.txt
