Metadata-Version: 2.1
Name: soothsayer
Version: 2022.8.31
Summary: High-level package for (bio-)informatics
Home-page: https://github.com/jolespin/soothsayer
Author: Josh L. Espinoza
Author-email: jespinoz@jcvi.org
License: BSD-3
License-File: LICENSE
